blogorama/__init__.py
blogorama/__version__.py
blogorama/admin.py
blogorama/apps.py
blogorama/forms.py
blogorama/mixin.py
blogorama/models.py
blogorama/settings.py
blogorama/tests.py
blogorama/utils.py
blogorama/api/seriealizers.py
blogorama/api/urls.py
blogorama/api/views.py
blogorama/migrations/0001_initial.py
blogorama/migrations/0002_comment_active_comment_post_alter_ban_created_and_more.py
blogorama/migrations/0003_alter_postflag_options.py
blogorama/migrations/__init__.py
blogorama/templates/blogorama/base.html
blogorama/templates/blogorama/post_detail.html
blogorama/templates/blogorama/post_form.html
blogorama/templates/blogorama/post_list.html
blogorama/templates/blogorama/post_update.html
blogorama/urls/__import__.py
blogorama/urls/blog.py
blogorama/views/__import__.py
blogorama/views/blog.py
django_blogorama-0.1.4.dist-info/METADATA
django_blogorama-0.1.4.dist-info/WHEEL
django_blogorama-0.1.4.dist-info/top_level.txt
django_blogorama-0.1.4.dist-info/RECORD
